Ravi_Weather.py
Ravi_Weather-0.0.3.dist-info/LICENSE
Ravi_Weather-0.0.3.dist-info/METADATA
Ravi_Weather-0.0.3.dist-info/WHEEL
Ravi_Weather-0.0.3.dist-info/top_level.txt
Ravi_Weather-0.0.3.dist-info/RECORD
