Metadata-Version: 2.1
Name: Ravi-Weather
Version: 0.0.3
Summary: A GUI Music Player with all the basic functions, which is developed using Tkinter
Home-page: UNKNOWN
Author: Ravi vardhan
License: UNKNOWN
Keywords: music player python,music player tkinter,music player gui
Platform: UNKNOWN
Classifier: Programming Language :: Python :: 3
Classifier: License :: OSI Approved :: MIT License
Classifier: Operating System :: OS Independent
Requires-Python: >=3.6
License-File: LICENSE
Requires-Dist: mutagen
Requires-Dist: pygame
Requires-Dist: ttkthemes
